TransactionUtility/Dynamic_Table_Creation.py
TransactionUtility/Function_Defination.py
TransactionUtility/GenerateBrowMetadataXML.py
TransactionUtility/GenerateEditMetadataXML.py
TransactionUtility/Generate_Transcation.py
TransactionUtility/Genmst.py
TransactionUtility/Genmst_Appl.py
TransactionUtility/Obj_Actions.py
TransactionUtility/Obj_Attach_Config.py
TransactionUtility/Obj_Followup_Act.py
TransactionUtility/Obj_Forms.py
TransactionUtility/Obj_Itemchange.py
TransactionUtility/Obj_Links.py
TransactionUtility/Pophelp.py
TransactionUtility/Sd_Trans_Design.py
TransactionUtility/TransDatabaseAmazonRedshift.py
TransactionUtility/TransDatabaseDremio.py
TransactionUtility/TransDatabaseGoogleBigQuery.py
TransactionUtility/TransDatabaseInMemory.py
TransactionUtility/TransDatabaseMSSQLServer.py
TransactionUtility/TransDatabaseMySql.py
TransactionUtility/TransDatabaseOracle.py
TransactionUtility/TransDatabasePostgress.py
TransactionUtility/TransDatabaseSAPHANA.py
TransactionUtility/TransDatabaseSnowFlake.py
TransactionUtility/TransDatabasecatlog.py
TransactionUtility/Transetup.py
TransactionUtility/__init__.py
transactionutility-0.0.55.dist-info/LICENCE.txt
transactionutility-0.0.55.dist-info/METADATA
transactionutility-0.0.55.dist-info/WHEEL
transactionutility-0.0.55.dist-info/top_level.txt
transactionutility-0.0.55.dist-info/RECORD
